kafka_utils/__init__.py
kafka_utils/kafka_client.py
kafka_utils/logger.py
kafka_tool_kit-1.0.0.dist-info/METADATA
kafka_tool_kit-1.0.0.dist-info/WHEEL
kafka_tool_kit-1.0.0.dist-info/top_level.txt
kafka_tool_kit-1.0.0.dist-info/RECORD
