Metadata-Version: 2.1
Name: kafka-tool-kit
Version: 1.0.0
Summary: A simple Kafka utility library using confluent-kafka
Home-page: UNKNOWN
Author: Triton Tech Labs.,
License: UNKNOWN
Platform: UNKNOWN
Requires-Python: >=3.7
Requires-Dist: confluent-kafka>=2.3.0
